met/__init__.py
met/__main__.py
met/met.py
pymetronome-0.1.0.dist-info/LICENSE
pymetronome-0.1.0.dist-info/METADATA
pymetronome-0.1.0.dist-info/WHEEL
pymetronome-0.1.0.dist-info/entry_points.txt
pymetronome-0.1.0.dist-info/top_level.txt
pymetronome-0.1.0.dist-info/RECORD
