Metadata-Version: 2.1
Name: pymetronome
Version: 0.1.0
Summary: A simple metronome utility
Home-page: https://github.com/spyoungtech/pymetronome
Author: Spencer Phillip Young
Author-email: spencer.young@spyoung.com
License: MIT
Platform: UNKNOWN
